pulp_container/__init__.py
pulp_container/constants.py
pulp_container/app/__init__.py
pulp_container/app/access_policy.py
pulp_container/app/authorization.py
pulp_container/app/cache.py
pulp_container/app/checks.py
pulp_container/app/content.py
pulp_container/app/downloaders.py
pulp_container/app/dynaconf_hooks.py
pulp_container/app/exceptions.py
pulp_container/app/fields.py
pulp_container/app/global_access_conditions.py
pulp_container/app/json_schemas.py
pulp_container/app/modelresource.py
pulp_container/app/models.py
pulp_container/app/redirects.py
pulp_container/app/registry.py
pulp_container/app/registry_api.py
pulp_container/app/replica.py
pulp_container/app/serializers.py
pulp_container/app/settings.py
pulp_container/app/token_verification.py
pulp_container/app/urls.py
pulp_container/app/utils.py
pulp_container/app/viewsets.py
pulp_container/app/management/__init__.py
pulp_container/app/management/commands/__init__.py
pulp_container/app/management/commands/container-handle-image-data.py
pulp_container/app/management/commands/container-repair-media-type.py
pulp_container/app/migrations/0001_initial.py
pulp_container/app/migrations/0001_squashed_0032_upload_artifact.py
pulp_container/app/migrations/0002_containerrepository.py
pulp_container/app/migrations/0003_oci_mediatype.py
pulp_container/app/migrations/0004_upload.py
pulp_container/app/migrations/0005_contentredirectcontentguard.py
pulp_container/app/migrations/0006_containerpushrepository.py
pulp_container/app/migrations/0007_clear_tags_artifacts_refs.py
pulp_container/app/migrations/0008_include_exclude_tags.py
pulp_container/app/migrations/0009_container_namespace.py
pulp_container/app/migrations/0010_remove_uploadchunk.py
pulp_container/app/migrations/0011_add_container_repository_permissions.py
pulp_container/app/migrations/0012_add_container_namespace_permissions.py
pulp_container/app/migrations/0013_add_pull_push_permissions.py
pulp_container/app/migrations/0014_containerdistribution_private.py
pulp_container-2.27.0.dist-info/licenses/LICENSE
pulp_container-2.27.0.dist-info/METADATA
pulp_container-2.27.0.dist-info/WHEEL
pulp_container-2.27.0.dist-info/entry_points.txt
pulp_container-2.27.0.dist-info/top_level.txt
pulp_container-2.27.0.dist-info/RECORD
