Metadata-Version: 2.4
Name: pulp-container
Version: 2.27.0
Summary: Container plugin for the Pulp Project
Author-email: Pulp Team <pulp-list@redhat.com>
Project-URL: Homepage, https://pulpproject.org
Project-URL: Documentation, https://pulpproject.org/pulp_container/
Project-URL: Repository, https://github.com/pulp/pulp_container
Project-URL: Bug Tracker, https://github.com/pulp/pulp_container/issues
Project-URL: Changelog, https://pulpproject.org/pulp_container/changes/
Classifier: License :: OSI Approved :: GNU General Public License v2 or later (GPLv2+)
Classifier: Operating System :: POSIX :: Linux
Classifier: Development Status :: 5 - Production/Stable
Classifier: Framework :: Django
Classifier: Programming Language :: Python
Classifier: Programming Language :: Python :: 3
Requires-Python: >=3.11
License-File: LICENSE
Requires-Dist: jsonschema<4.26,>=4.4
Requires-Dist: pulpcore<3.115,>=3.73.2
Requires-Dist: pyjwt[crypto]<2.11,>=2.4
Dynamic: license-file
